{
  "schemaVersion": "component-qualification-evidence/v1",
  "componentType": "CtaBanner",
  "part": "fixtures",
  "status": "pass",
  "fixtureFiles": [
    {
      "fixtureId": "technical-baseline",
      "repositoryPath": "apps/site-renderer/fixtures/technical-baseline-spec.json",
      "sha256": "e3831bd6bb2d673de4e88b1aafeb928d316249c4a42685df2c065f985d9d0aab"
    }
  ],
  "assertions": [
    "The fixture uses bounded copy and the explicit technical-grid variant."
  ],
  "verification": ["pnpm --filter @global/site-renderer test:visual"]
}
